jxrd_stock_strategy_pkg/__init__.py
jxrd_stock_strategy_pkg/number_utils.py
jxrd_stock_strategy_pkg/params.py
jxrd_stock_strategy_pkg/strategy.py
jxrd_stock_strategy-0.1.dist-info/METADATA
jxrd_stock_strategy-0.1.dist-info/WHEEL
jxrd_stock_strategy-0.1.dist-info/top_level.txt
jxrd_stock_strategy-0.1.dist-info/RECORD
