Metadata-Version: 2.1
Name: jxrd_stock_strategy
Version: 0.1
Summary: stock strategy package
Author: Ray.Yuan
Author-email: yuanlei5118@163.com
License: MIT
Classifier: Programming Language :: Python :: 3
Classifier: License :: OSI Approved :: MIT License
Classifier: Operating System :: OS Independent
Requires-Python: >=3.6
